<?xml version="1.0" encoding="UTF-8"?>
<!DOCTYPE mapper PUBLIC "-//mybatis.org//DTD Mapper 3.0//EN"
        "http://mybatis.org/dtd/mybatis-3-mapper.dtd">

<mapper namespace="com.saffron.qbank.mapper.ExamSessionMapper">

    <resultMap id="ExamSessionResultMap" type="com.saffron.qbank.domain.ExamSession">
        <id     property="id"           column="id"/>
        <result property="examPaperId"  column="examPaperId"/>
        <result property="examineeName" column="examineeName"/>
        <result property="examineeNo"   column="examineeNo"/>
        <result property="startedAt"    column="startedAt"/>
        <result property="submittedAt"  column="submittedAt"/>
        <result property="totalScore"   column="totalScore"/>
    </resultMap>

    <select id="selectAll" resultMap="ExamSessionResultMap">
        SELECT id, examPaperId, examineeName, examineeNo, startedAt, submittedAt, totalScore
        FROM qbank_exam_session
        <where>
            <if test="paperId != null">AND examPaperId = #{paperId}</if>
            <if test="examineeName != null and examineeName != ''">
                AND examineeName LIKE CONCAT('%', #{examineeName}, '%')
            </if>
        </where>
        ORDER BY startedAt DESC
    </select>

    <select id="selectById" resultMap="ExamSessionResultMap">
        SELECT id, examPaperId, examineeName, examineeNo, startedAt, submittedAt, totalScore
        FROM qbank_exam_session
        WHERE id = #{id}
    </select>

    <insert id="insert" parameterType="com.saffron.qbank.domain.ExamSession"
            useGeneratedKeys="true" keyProperty="id">
        INSERT INTO qbank_exam_session (examPaperId, examineeName, examineeNo)
        VALUES (#{examPaperId}, #{examineeName}, #{examineeNo})
    </insert>

    <update id="updateSubmitted">
        UPDATE qbank_exam_session
        SET submittedAt = NOW()
        WHERE id = #{id}
    </update>

    <update id="updateTotalScore">
        UPDATE qbank_exam_session
        SET totalScore = #{totalScore}
        WHERE id = #{id}
    </update>

</mapper>
